PySubtitle/__init__.py
PySubtitle/audio_extraction.py
PySubtitle/languages.py
PySubtitle/speech_recognition.py
PySubtitle/vtt_generation.py
tests/__init__.py
tests/test_audio_extraction.py
tests/test_speech_recognition.py
tests/test_vtt_generation.py
PySubtitle-0.1.2.dist-info/LICENSE
PySubtitle-0.1.2.dist-info/METADATA
PySubtitle-0.1.2.dist-info/WHEEL
PySubtitle-0.1.2.dist-info/top_level.txt
PySubtitle-0.1.2.dist-info/RECORD
