Metadata-Version: 2.1
Name: PySubtitle
Version: 0.1.2
Summary: A python library to generate subtitles from a video
Home-page: https://github.com/Shadows97/PySubtitle
Author: Shadows97
Author-email: mpoderrick97@gmail.com
License: UNKNOWN
Platform: UNKNOWN
Classifier: Development Status :: 3 - Alpha
Classifier: Intended Audience :: Developers
Classifier: License :: OSI Approved :: MIT License
Classifier: Programming Language :: Python :: 3
Classifier: Programming Language :: Python :: 3.7
Classifier: Programming Language :: Python :: 3.8
Classifier: Programming Language :: Python :: 3.9
License-File: LICENSE
Requires-Dist: ffmpeg-python
Requires-Dist: pydub
Requires-Dist: SpeechRecognition
Requires-Dist: webvtt-py
